structional/__init__.py
structional/_better_abstract.py
structional/_misc.py
structional/_random.py
structional/_random_fixture.py
structional/_struct.py
structional/tree/__init__.py
structional/tree/_tree.py
structional-0.4.0.dist-info/METADATA
structional-0.4.0.dist-info/WHEEL
structional-0.4.0.dist-info/licenses/LICENSE
structional-0.4.0.dist-info/RECORD
