Metadata-Version: 2.4
Name: structional
Version: 0.4.0
Summary: Immutable structs, controlled randomness, and trees. These are the core tools I use to build reliable software in Python.
Project-URL: repository, https://github.com/patrick-kidger/structional
Author-email: Patrick Kidger <contact@kidger.site>
License:                                  Apache License
License-File: LICENSE
Classifier: Development Status :: 3 - Alpha
Classifier: Intended Audience :: Developers
Classifier: Intended Audience :: Financial and Insurance Industry
Classifier: Intended Audience :: Information Technology
Classifier: Intended Audience :: Science/Research
Classifier: License :: OSI Approved :: Apache Software License
Classifier: Natural Language :: English
Classifier: Programming Language :: Python :: 3
Classifier: Topic :: Scientific/Engineering :: Artificial Intelligence
Classifier: Topic :: Scientific/Engineering :: Information Analysis
Classifier: Topic :: Scientific/Engineering :: Mathematics
Requires-Python: >=3.11
Requires-Dist: jaxtyping>=0.3.3
Requires-Dist: typing-extensions>=4.5.0
Requires-Dist: wadler-lindig>=0.1.0
